{
	"credit": "Made with Blockbench",
	"parent": "block/block",
	"textures": {
		"0": "block/ruins_pot_blue",
		"particle": "block/ruins_pot_blue"
	},
	"elements": [
		{
			"from": [5.5, 8, 5.5],
			"to": [10.5, 10, 10.5],
			"color": 5,
			"faces": {
				"north": {"uv": [2, 2, 7, 2.9], "texture": "#missing"},
				"east": {"uv": [2, 2, 7, 2.9], "texture": "#missing"},
				"south": {"uv": [2, 2, 7, 2.9], "texture": "#missing"},
				"west": {"uv": [2, 2, 7, 2.9], "texture": "#missing"},
				"up": {"uv": [2, 3, 7, 3.9], "texture": "#missing"},
				"down": {"uv": [2, 2, 7, 2.9], "texture": "#missing"}
			}
		},
		{
			"from": [5.5, 8, 5.5],
			"to": [10.5, 10, 10.5],
			"faces": {
				"north": {"uv": [2, 2, 7, 2.9], "texture": "#0"},
				"east": {"uv": [2, 2, 7, 2.9], "texture": "#0"},
				"south": {"uv": [2, 2, 7, 2.9], "texture": "#0"},
				"west": {"uv": [2, 2, 7, 2.9], "texture": "#0"},
				"up": {"uv": [2, 3, 7, 3.9], "texture": "#0"},
				"down": {"uv": [2, 2, 7, 2.9], "texture": "#0"}
			}
		},
		{
			"from": [5.5, 10, 10.5],
			"to": [10.5, 12, 12.5],
			"color": 1,
			"faces": {
				"north": {"uv": [2, 5, 7, 5.9], "texture": "#missing"},
				"east": {"uv": [2, 5, 7, 5.9], "texture": "#missing"},
				"south": {"uv": [2, 5, 7, 5.9], "texture": "#missing"},
				"west": {"uv": [2, 5, 7, 5.9], "texture": "#missing"},
				"up": {"uv": [2, 2, 7, 2.9], "texture": "#missing"},
				"down": {"uv": [2, 5, 7, 5.9], "texture": "#missing"}
			}
		},
		{
			"from": [5.5, 10, 10.5],
			"to": [10.5, 12, 12.5],
			"faces": {
				"north": {"uv": [2, 5, 7, 5.9], "texture": "#0"},
				"east": {"uv": [2, 5, 7, 5.9], "texture": "#0"},
				"south": {"uv": [2, 5, 7, 5.9], "texture": "#0"},
				"west": {"uv": [2, 5, 7, 5.9], "texture": "#0"},
				"up": {"uv": [2, 2, 7, 2.9], "texture": "#0"},
				"down": {"uv": [2, 5, 7, 5.9], "texture": "#0"}
			}
		},
		{
			"from": [4.5, 0, 4.5],
			"to": [11.5, 8, 11.5],
			"color": 1,
			"faces": {
				"north": {"uv": [0, 9, 1, 15], "texture": "#missing"},
				"east": {"uv": [0, 9, 1, 15], "texture": "#missing"},
				"south": {"uv": [0, 9, 1, 15], "texture": "#missing"},
				"west": {"uv": [0, 9, 1, 15], "texture": "#missing"},
				"up": {"uv": [0, 9, 1, 15], "texture": "#missing"},
				"down": {"uv": [7, 10, 8, 16], "texture": "#missing"}
			}
		},
		{
			"from": [4.5, 0, 4.5],
			"to": [11.5, 8, 11.5],
			"faces": {
				"north": {"uv": [0, 9, 1, 15], "texture": "#0"},
				"east": {"uv": [0, 9, 1, 15], "texture": "#0"},
				"south": {"uv": [0, 9, 1, 15], "texture": "#0"},
				"west": {"uv": [0, 9, 1, 15], "texture": "#0"},
				"up": {"uv": [0, 9, 1, 15], "texture": "#0"},
				"down": {"uv": [7, 10, 8, 16], "texture": "#0"}
			}
		},
		{
			"from": [11.5, 1, 4.5],
			"to": [12.5, 7, 11.5],
			"color": 1,
			"faces": {
				"north": {"uv": [0, 9, 1, 15], "texture": "#missing"},
				"east": {"uv": [1, 9, 8, 15], "texture": "#missing"},
				"south": {"uv": [0, 9, 1, 15], "texture": "#missing"},
				"west": {"uv": [0, 0, 7, 6], "texture": "#missing"},
				"up": {"uv": [0, 9, 1, 15], "texture": "#missing"},
				"down": {"uv": [7, 10, 8, 16], "texture": "#missing"}
			}
		},
		{
			"from": [11.5, 1, 4.5],
			"to": [12.5, 7, 11.5],
			"faces": {
				"north": {"uv": [0, 9, 1, 15], "texture": "#0"},
				"east": {"uv": [1, 9, 8, 15], "texture": "#0"},
				"south": {"uv": [0, 9, 1, 15], "texture": "#0"},
				"west": {"uv": [0, 0, 7, 6], "texture": "#0"},
				"up": {"uv": [0, 9, 1, 15], "texture": "#0"},
				"down": {"uv": [7, 10, 8, 16], "texture": "#0"}
			}
		},
		{
			"from": [3.5, 1, 4.5],
			"to": [4.5, 7, 11.5],
			"faces": {
				"north": {"uv": [0, 9, 1, 15], "texture": "#missing"},
				"east": {"uv": [0, 0, 7, 6], "texture": "#missing"},
				"south": {"uv": [0, 9, 1, 15], "texture": "#missing"},
				"west": {"uv": [1, 9, 8, 15], "texture": "#0"},
				"up": {"uv": [0, 9, 1, 15], "texture": "#missing"},
				"down": {"uv": [7, 10, 8, 16], "texture": "#missing"}
			}
		},
		{
			"from": [3.5, 1, 4.5],
			"to": [4.5, 7, 11.5],
			"faces": {
				"north": {"uv": [0, 9, 1, 15], "texture": "#0"},
				"east": {"uv": [0, 0, 7, 6], "texture": "#0"},
				"south": {"uv": [0, 9, 1, 15], "texture": "#0"},
				"west": {"uv": [1, 9, 8, 15], "texture": "#0"},
				"up": {"uv": [0, 9, 1, 15], "texture": "#0"},
				"down": {"uv": [7, 10, 8, 16], "texture": "#0"}
			}
		},
		{
			"from": [4.5, 1, 11.5],
			"to": [11.5, 7, 12.5],
			"color": 4,
			"faces": {
				"north": {"uv": [0, 0, 7, 6], "texture": "#missing"},
				"east": {"uv": [0, 9, 1, 15], "texture": "#missing"},
				"south": {"uv": [1, 9, 8, 15], "texture": "#missing"},
				"west": {"uv": [0, 9, 1, 15], "texture": "#missing"},
				"up": {"uv": [0, 9, 1, 15], "texture": "#missing"},
				"down": {"uv": [7, 10, 8, 16], "texture": "#missing"}
			}
		},
		{
			"from": [4.5, 1, 11.5],
			"to": [11.5, 7, 12.5],
			"faces": {
				"north": {"uv": [0, 0, 7, 6], "texture": "#0"},
				"east": {"uv": [0, 9, 1, 15], "texture": "#0"},
				"south": {"uv": [1, 9, 8, 15], "texture": "#0"},
				"west": {"uv": [0, 9, 1, 15], "texture": "#0"},
				"up": {"uv": [0, 9, 1, 15], "texture": "#0"},
				"down": {"uv": [7, 10, 8, 16], "texture": "#0"}
			}
		},
		{
			"from": [4.5, 1, 3.5],
			"to": [11.5, 7, 4.5],
			"color": 2,
			"faces": {
				"north": {"uv": [1, 9, 8, 15], "texture": "#missing"},
				"east": {"uv": [0, 9, 1, 15], "texture": "#missing"},
				"south": {"uv": [0, 0, 7, 6], "texture": "#missing"},
				"west": {"uv": [0, 9, 1, 15], "texture": "#missing"},
				"up": {"uv": [0, 9, 1, 15], "texture": "#missing"},
				"down": {"uv": [7, 10, 8, 16], "texture": "#missing"}
			}
		},
		{
			"from": [4.5, 1, 3.5],
			"to": [11.5, 7, 4.5],
			"faces": {
				"north": {"uv": [1, 9, 8, 15], "texture": "#0"},
				"east": {"uv": [0, 9, 1, 15], "texture": "#0"},
				"south": {"uv": [0, 0, 7, 6], "texture": "#0"},
				"west": {"uv": [0, 9, 1, 15], "texture": "#0"},
				"up": {"uv": [0, 9, 1, 15], "texture": "#0"},
				"down": {"uv": [7, 10, 8, 16], "texture": "#0"}
			}
		},
		{
			"from": [5.5, 10.1, 3.5],
			"to": [10.5, 12, 5.5],
			"color": 2,
			"faces": {
				"north": {"uv": [2, 5, 7, 5.9], "texture": "#missing"},
				"east": {"uv": [2, 5, 7, 5.9], "texture": "#missing"},
				"south": {"uv": [2, 5, 7, 5.9], "texture": "#missing"},
				"west": {"uv": [2, 5, 7, 5.9], "texture": "#missing"},
				"up": {"uv": [2, 2, 7, 2.9], "texture": "#missing"},
				"down": {"uv": [2, 5, 7, 5.9], "texture": "#missing"}
			}
		},
		{
			"from": [5.5, 10.1, 3.5],
			"to": [10.5, 12, 5.5],
			"faces": {
				"north": {"uv": [2, 5, 7, 5.9], "texture": "#0"},
				"east": {"uv": [2, 5, 7, 5.9], "texture": "#0"},
				"south": {"uv": [2, 5, 7, 5.9], "texture": "#0"},
				"west": {"uv": [2, 5, 7, 5.9], "texture": "#0"},
				"up": {"uv": [2, 2, 7, 2.9], "texture": "#0"},
				"down": {"uv": [2, 5, 7, 5.9], "texture": "#0"}
			}
		},
		{
			"from": [10.5, 10.1, 5.5],
			"to": [12.5, 12, 10.5],
			"color": 0,
			"faces": {
				"north": {"uv": [2, 5, 7, 5.9], "texture": "#missing"},
				"east": {"uv": [2, 5, 7, 5.9], "texture": "#missing"},
				"south": {"uv": [2, 5, 7, 5.9], "texture": "#missing"},
				"west": {"uv": [2, 5, 7, 5.9], "texture": "#missing"},
				"up": {"uv": [2, 2, 7, 2.9], "texture": "#missing"},
				"down": {"uv": [2, 5, 7, 5.9], "texture": "#missing"}
			}
		},
		{
			"from": [10.5, 10.1, 5.5],
			"to": [12.5, 12, 10.5],
			"faces": {
				"north": {"uv": [2, 5, 7, 5.9], "texture": "#0"},
				"east": {"uv": [2, 5, 7, 5.9], "texture": "#0"},
				"south": {"uv": [2, 5, 7, 5.9], "texture": "#0"},
				"west": {"uv": [2, 5, 7, 5.9], "texture": "#0"},
				"up": {"uv": [2, 2, 7, 2.9], "texture": "#0"},
				"down": {"uv": [2, 5, 7, 5.9], "texture": "#0"}
			}
		},
		{
			"from": [3.5, 10, 5.5],
			"to": [5.5, 12, 10.5],
			"color": 2,
			"faces": {
				"north": {"uv": [2, 5, 7, 5.9], "texture": "#missing"},
				"east": {"uv": [2, 5, 7, 5.9], "texture": "#missing"},
				"south": {"uv": [2, 5, 7, 5.9], "texture": "#missing"},
				"west": {"uv": [2, 5, 7, 5.9], "texture": "#missing"},
				"up": {"uv": [2, 2, 7, 2.9], "texture": "#missing"},
				"down": {"uv": [2, 5, 7, 5.9], "texture": "#missing"}
			}
		},
		{
			"from": [3.5, 10, 5.5],
			"to": [5.5, 12, 10.5],
			"faces": {
				"north": {"uv": [2, 5, 7, 5.9], "texture": "#0"},
				"east": {"uv": [2, 5, 7, 5.9], "texture": "#0"},
				"south": {"uv": [2, 5, 7, 5.9], "texture": "#0"},
				"west": {"uv": [2, 5, 7, 5.9], "texture": "#0"},
				"up": {"uv": [2, 2, 7, 2.9], "texture": "#0"},
				"down": {"uv": [2, 5, 7, 5.9], "texture": "#0"}
			}
		}
	]
}